[
  {
    "ce_loss": 2.30747652053833,
    "learning_rate": 0.001,
    "pairwise_loss": 0.0,
    "resistance_supervision_loss": 0.0,
    "step": 1,
    "train_accuracy": 0.078125,
    "train_loss": 2.30747652053833,
    "wall_clock_time_sec": 0.004146575927734375
  },
  {
    "ce_loss": 2.292970657348633,
    "learning_rate": 0.001,
    "pairwise_loss": 0.0,
    "resistance_supervision_loss": 0.0,
    "step": 2,
    "train_accuracy": 0.15625,
    "train_loss": 2.292970657348633,
    "wall_clock_time_sec": 0.0069849491119384766
  },
  {
    "ce_loss": 2.2846667766571045,
    "learning_rate": 0.001,
    "pairwise_loss": 0.0,
    "resistance_supervision_loss": 0.0,
    "step": 3,
    "train_accuracy": 0.265625,
    "train_loss": 2.2846667766571045,
    "wall_clock_time_sec": 0.01072239875793457
  },
  {
    "ce_loss": 2.2701103687286377,
    "learning_rate": 0.001,
    "pairwise_loss": 0.0,
    "resistance_supervision_loss": 0.0,
    "step": 4,
    "train_accuracy": 0.359375,
    "train_loss": 2.2701103687286377,
    "wall_clock_time_sec": 0.013641357421875
  },
  {
    "ce_loss": 2.2512502670288086,
    "learning_rate": 0.001,
    "pairwise_loss": 0.0,
    "resistance_supervision_loss": 0.0,
    "step": 5,
    "train_accuracy": 0.34375,
    "train_loss": 2.2512502670288086,
    "wall_clock_time_sec": 0.017374515533447266
  },
  {
    "ce_loss": 2.248851776123047,
    "learning_rate": 0.001,
    "pairwise_loss": 0.0,
    "resistance_supervision_loss": 0.0,
    "step": 6,
    "train_accuracy": 0.28125,
    "train_loss": 2.248851776123047,
    "wall_clock_time_sec": 0.021069049835205078
  },
  {
    "ce_loss": 2.226957321166992,
    "learning_rate": 0.001,
    "pairwise_loss": 0.0,
    "resistance_supervision_loss": 0.0,
    "step": 7,
    "train_accuracy": 0.40625,
    "train_loss": 2.226957321166992,
    "wall_clock_time_sec": 0.024838685989379883
  },
  {
    "ce_loss": 2.221571922302246,
    "learning_rate": 0.001,
    "pairwise_loss": 0.0,
    "resistance_supervision_loss": 0.0,
    "step": 8,
    "train_accuracy": 0.25,
    "train_loss": 2.221571922302246,
    "wall_clock_time_sec": 0.028516530990600586
  },
  {
    "ce_loss": 2.2133610248565674,
    "learning_rate": 0.001,
    "pairwise_loss": 0.0,
    "resistance_supervision_loss": 0.0,
    "step": 9,
    "train_accuracy": 0.34375,
    "train_loss": 2.2133610248565674,
    "wall_clock_time_sec": 0.03279232978820801
  },
  {
    "ce_loss": 2.176091432571411,
    "learning_rate": 0.001,
    "pairwise_loss": 0.0,
    "resistance_supervision_loss": 0.0,
    "step": 10,
    "train_accuracy": 0.390625,
    "train_loss": 2.176091432571411,
    "wall_clock_time_sec": 0.03695392608642578
  },
  {
    "ce_loss": 2.168826103210449,
    "learning_rate": 0.001,
    "pairwise_loss": 0.0,
    "resistance_supervision_loss": 0.0,
    "step": 11,
    "train_accuracy": 0.421875,
    "train_loss": 2.168826103210449,
    "wall_clock_time_sec": 0.04195809364318848
  },
  {
    "ce_loss": 2.149601459503174,
    "learning_rate": 0.001,
    "pairwise_loss": 0.0,
    "resistance_supervision_loss": 0.0,
    "step": 12,
    "train_accuracy": 0.484375,
    "train_loss": 2.149601459503174,
    "wall_clock_time_sec": 0.04530906677246094
  },
  {
    "ce_loss": 2.1306047439575195,
    "learning_rate": 0.001,
    "pairwise_loss": 0.0,
    "resistance_supervision_loss": 0.0,
    "step": 13,
    "train_accuracy": 0.46875,
    "train_loss": 2.1306047439575195,
    "wall_clock_time_sec": 0.05067586898803711
  },
  {
    "ce_loss": 2.106311321258545,
    "learning_rate": 0.001,
    "pairwise_loss": 0.0,
    "resistance_supervision_loss": 0.0,
    "step": 14,
    "train_accuracy": 0.453125,
    "train_loss": 2.106311321258545,
    "wall_clock_time_sec": 0.054129600524902344
  },
  {
    "ce_loss": 2.104346752166748,
    "learning_rate": 0.001,
    "pairwise_loss": 0.0,
    "resistance_supervision_loss": 0.0,
    "step": 15,
    "train_accuracy": 0.453125,
    "train_loss": 2.104346752166748,
    "wall_clock_time_sec": 0.0579073429107666
  },
  {
    "ce_loss": 2.0741701126098633,
    "learning_rate": 0.001,
    "pairwise_loss": 0.0,
    "resistance_supervision_loss": 0.0,
    "step": 16,
    "train_accuracy": 0.421875,
    "train_loss": 2.0741701126098633,
    "wall_clock_time_sec": 0.061852455139160156
  },
  {
    "ce_loss": 2.0612070560455322,
    "learning_rate": 0.001,
    "pairwise_loss": 0.0,
    "resistance_supervision_loss": 0.0,
    "step": 17,
    "train_accuracy": 0.453125,
    "train_loss": 2.0612070560455322,
    "wall_clock_time_sec": 0.06587743759155273
  },
  {
    "ce_loss": 2.0097384452819824,
    "learning_rate": 0.001,
    "pairwise_loss": 0.0,
    "resistance_supervision_loss": 0.0,
    "step": 18,
    "train_accuracy": 0.546875,
    "train_loss": 2.0097384452819824,
    "wall_clock_time_sec": 0.07027077674865723
  },
  {
    "ce_loss": 2.013631820678711,
    "learning_rate": 0.001,
    "pairwise_loss": 0.0,
    "resistance_supervision_loss": 0.0,
    "step": 19,
    "train_accuracy": 0.296875,
    "train_loss": 2.013631820678711,
    "wall_clock_time_sec": 0.07422828674316406
  },
  {
    "ce_loss": 1.982288122177124,
    "learning_rate": 0.001,
    "pairwise_loss": 0.0,
    "resistance_supervision_loss": 0.0,
    "step": 20,
    "train_accuracy": 0.4375,
    "train_loss": 1.982288122177124,
    "wall_clock_time_sec": 0.07818794250488281
  },
  {
    "ce_loss": 2.0000157356262207,
    "learning_rate": 0.001,
    "pairwise_loss": 0.0,
    "resistance_supervision_loss": 0.0,
    "step": 21,
    "train_accuracy": 0.453125,
    "train_loss": 2.0000157356262207,
    "wall_clock_time_sec": 0.08269333839416504
  },
  {
    "ce_loss": 1.9632935523986816,
    "learning_rate": 0.001,
    "pairwise_loss": 0.0,
    "resistance_supervision_loss": 0.0,
    "step": 22,
    "train_accuracy": 0.40625,
    "train_loss": 1.9632935523986816,
    "wall_clock_time_sec": 0.08686685562133789
  },
  {
    "ce_loss": 1.8850977420806885,
    "learning_rate": 0.001,
    "pairwise_loss": 0.0,
    "resistance_supervision_loss": 0.0,
    "step": 23,
    "train_accuracy": 0.5625,
    "train_loss": 1.8850977420806885,
    "wall_clock_time_sec": 0.09146595001220703
  },
  {
    "ce_loss": 1.8524574041366577,
    "learning_rate": 0.001,
    "pairwise_loss": 0.0,
    "resistance_supervision_loss": 0.0,
    "step": 24,
    "train_accuracy": 0.53125,
    "train_loss": 1.8524574041366577,
    "wall_clock_time_sec": 0.0959475040435791
  },
  {
    "ce_loss": 1.754376769065857,
    "learning_rate": 0.001,
    "pairwise_loss": 0.0,
    "resistance_supervision_loss": 0.0,
    "step": 25,
    "train_accuracy": 0.515625,
    "train_loss": 1.754376769065857,
    "val_accuracy": 0.3828125,
    "val_ece": 0.18159721791744232,
    "wall_clock_time_sec": 0.1005244255065918
  },
  {
    "ce_loss": 1.828703761100769,
    "learning_rate": 0.001,
    "pairwise_loss": 0.0,
    "resistance_supervision_loss": 0.0,
    "step": 26,
    "train_accuracy": 0.46875,
    "train_loss": 1.828703761100769,
    "wall_clock_time_sec": 0.17723321914672852
  },
  {
    "ce_loss": 1.7447264194488525,
    "learning_rate": 0.001,
    "pairwise_loss": 0.0,
    "resistance_supervision_loss": 0.0,
    "step": 27,
    "train_accuracy": 0.453125,
    "train_loss": 1.7447264194488525,
    "wall_clock_time_sec": 0.18175363540649414
  },
  {
    "ce_loss": 1.7482292652130127,
    "learning_rate": 0.001,
    "pairwise_loss": 0.0,
    "resistance_supervision_loss": 0.0,
    "step": 28,
    "train_accuracy": 0.453125,
    "train_loss": 1.7482292652130127,
    "wall_clock_time_sec": 0.1893904209136963
  },
  {
    "ce_loss": 1.7775429487228394,
    "learning_rate": 0.001,
    "pairwise_loss": 0.0,
    "resistance_supervision_loss": 0.0,
    "step": 29,
    "train_accuracy": 0.421875,
    "train_loss": 1.7775429487228394,
    "wall_clock_time_sec": 0.19330596923828125
  },
  {
    "ce_loss": 1.6301426887512207,
    "learning_rate": 0.001,
    "pairwise_loss": 0.0,
    "resistance_supervision_loss": 0.0,
    "step": 30,
    "train_accuracy": 0.5,
    "train_loss": 1.6301426887512207,
    "wall_clock_time_sec": 0.1971580982208252
  },
  {
    "ce_loss": 1.7266093492507935,
    "learning_rate": 0.001,
    "pairwise_loss": 0.0,
    "resistance_supervision_loss": 0.0,
    "step": 31,
    "train_accuracy": 0.5,
    "train_loss": 1.7266093492507935,
    "wall_clock_time_sec": 0.20087313652038574
  },
  {
    "ce_loss": 1.5179044008255005,
    "learning_rate": 0.001,
    "pairwise_loss": 0.0,
    "resistance_supervision_loss": 0.0,
    "step": 32,
    "train_accuracy": 0.40625,
    "train_loss": 1.5179044008255005,
    "wall_clock_time_sec": 0.20393943786621094
  },
  {
    "ce_loss": 1.671415090560913,
    "learning_rate": 0.001,
    "pairwise_loss": 0.0,
    "resistance_supervision_loss": 0.0,
    "step": 33,
    "train_accuracy": 0.40625,
    "train_loss": 1.671415090560913,
    "wall_clock_time_sec": 0.2076282501220703
  },
  {
    "ce_loss": 1.501926064491272,
    "learning_rate": 0.001,
    "pairwise_loss": 0.0,
    "resistance_supervision_loss": 0.0,
    "step": 34,
    "train_accuracy": 0.453125,
    "train_loss": 1.501926064491272,
    "wall_clock_time_sec": 0.2113795280456543
  },
  {
    "ce_loss": 1.5487312078475952,
    "learning_rate": 0.001,
    "pairwise_loss": 0.0,
    "resistance_supervision_loss": 0.0,
    "step": 35,
    "train_accuracy": 0.578125,
    "train_loss": 1.5487312078475952,
    "wall_clock_time_sec": 0.21894240379333496
  },
  {
    "ce_loss": 1.4145041704177856,
    "learning_rate": 0.001,
    "pairwise_loss": 0.0,
    "resistance_supervision_loss": 0.0,
    "step": 36,
    "train_accuracy": 0.53125,
    "train_loss": 1.4145041704177856,
    "wall_clock_time_sec": 0.22265267372131348
  },
  {
    "ce_loss": 1.5549951791763306,
    "learning_rate": 0.001,
    "pairwise_loss": 0.0,
    "resistance_supervision_loss": 0.0,
    "step": 37,
    "train_accuracy": 0.46875,
    "train_loss": 1.5549951791763306,
    "wall_clock_time_sec": 0.22668147087097168
  },
  {
    "ce_loss": 1.5454986095428467,
    "learning_rate": 0.001,
    "pairwise_loss": 0.0,
    "resistance_supervision_loss": 0.0,
    "step": 38,
    "train_accuracy": 0.515625,
    "train_loss": 1.5454986095428467,
    "wall_clock_time_sec": 0.23071956634521484
  },
  {
    "ce_loss": 1.5927435159683228,
    "learning_rate": 0.001,
    "pairwise_loss": 0.0,
    "resistance_supervision_loss": 0.0,
    "step": 39,
    "train_accuracy": 0.453125,
    "train_loss": 1.5927435159683228,
    "wall_clock_time_sec": 0.23445749282836914
  },
  {
    "ce_loss": 1.566628098487854,
    "learning_rate": 0.001,
    "pairwise_loss": 0.0,
    "resistance_supervision_loss": 0.0,
    "step": 40,
    "train_accuracy": 0.421875,
    "train_loss": 1.566628098487854,
    "wall_clock_time_sec": 0.23843646049499512
  },
  {
    "ce_loss": 1.5815958976745605,
    "learning_rate": 0.001,
    "pairwise_loss": 0.0,
    "resistance_supervision_loss": 0.0,
    "step": 41,
    "train_accuracy": 0.484375,
    "train_loss": 1.5815958976745605,
    "wall_clock_time_sec": 0.2422177791595459
  },
  {
    "ce_loss": 1.5214424133300781,
    "learning_rate": 0.001,
    "pairwise_loss": 0.0,
    "resistance_supervision_loss": 0.0,
    "step": 42,
    "train_accuracy": 0.453125,
    "train_loss": 1.5214424133300781,
    "wall_clock_time_sec": 0.24604249000549316
  },
  {
    "ce_loss": 1.7175114154815674,
    "learning_rate": 0.001,
    "pairwise_loss": 0.0,
    "resistance_supervision_loss": 0.0,
    "step": 43,
    "train_accuracy": 0.28125,
    "train_loss": 1.7175114154815674,
    "wall_clock_time_sec": 0.24991917610168457
  },
  {
    "ce_loss": 1.4064944982528687,
    "learning_rate": 0.001,
    "pairwise_loss": 0.0,
    "resistance_supervision_loss": 0.0,
    "step": 44,
    "train_accuracy": 0.34375,
    "train_loss": 1.4064944982528687,
    "wall_clock_time_sec": 0.25417017936706543
  },
  {
    "ce_loss": 1.4851583242416382,
    "learning_rate": 0.001,
    "pairwise_loss": 0.0,
    "resistance_supervision_loss": 0.0,
    "step": 45,
    "train_accuracy": 0.5,
    "train_loss": 1.4851583242416382,
    "wall_clock_time_sec": 0.25806450843811035
  },
  {
    "ce_loss": 1.7309339046478271,
    "learning_rate": 0.001,
    "pairwise_loss": 0.0,
    "resistance_supervision_loss": 0.0,
    "step": 46,
    "train_accuracy": 0.390625,
    "train_loss": 1.7309339046478271,
    "wall_clock_time_sec": 0.26221275329589844
  },
  {
    "ce_loss": 1.5231478214263916,
    "learning_rate": 0.001,
    "pairwise_loss": 0.0,
    "resistance_supervision_loss": 0.0,
    "step": 47,
    "train_accuracy": 0.46875,
    "train_loss": 1.5231478214263916,
    "wall_clock_time_sec": 0.2660846710205078
  },
  {
    "ce_loss": 1.4874064922332764,
    "learning_rate": 0.001,
    "pairwise_loss": 0.0,
    "resistance_supervision_loss": 0.0,
    "step": 48,
    "train_accuracy": 0.40625,
    "train_loss": 1.4874064922332764,
    "wall_clock_time_sec": 0.27004265785217285
  },
  {
    "ce_loss": 1.4693679809570312,
    "learning_rate": 0.001,
    "pairwise_loss": 0.0,
    "resistance_supervision_loss": 0.0,
    "step": 49,
    "train_accuracy": 0.375,
    "train_loss": 1.4693679809570312,
    "wall_clock_time_sec": 0.2742612361907959
  },
  {
    "ce_loss": 1.5724517107009888,
    "learning_rate": 0.001,
    "pairwise_loss": 0.0,
    "resistance_supervision_loss": 0.0,
    "step": 50,
    "train_accuracy": 0.40625,
    "train_loss": 1.5724517107009888,
    "val_accuracy": 0.48046875,
    "val_ece": 0.08618897944688797,
    "wall_clock_time_sec": 0.2789428234100342
  },
  {
    "ce_loss": 1.3367458581924438,
    "learning_rate": 0.001,
    "pairwise_loss": 0.0,
    "resistance_supervision_loss": 0.0,
    "step": 51,
    "train_accuracy": 0.5,
    "train_loss": 1.3367458581924438,
    "wall_clock_time_sec": 0.43271303176879883
  },
  {
    "ce_loss": 1.4852265119552612,
    "learning_rate": 0.001,
    "pairwise_loss": 0.0,
    "resistance_supervision_loss": 0.0,
    "step": 52,
    "train_accuracy": 0.5,
    "train_loss": 1.4852265119552612,
    "wall_clock_time_sec": 0.4362950325012207
  },
  {
    "ce_loss": 1.5529862642288208,
    "learning_rate": 0.001,
    "pairwise_loss": 0.0,
    "resistance_supervision_loss": 0.0,
    "step": 53,
    "train_accuracy": 0.421875,
    "train_loss": 1.5529862642288208,
    "wall_clock_time_sec": 0.440075159072876
  },
  {
    "ce_loss": 1.348143219947815,
    "learning_rate": 0.001,
    "pairwise_loss": 0.0,
    "resistance_supervision_loss": 0.0,
    "step": 54,
    "train_accuracy": 0.5,
    "train_loss": 1.348143219947815,
    "wall_clock_time_sec": 0.44432854652404785
  },
  {
    "ce_loss": 1.5061442852020264,
    "learning_rate": 0.001,
    "pairwise_loss": 0.0,
    "resistance_supervision_loss": 0.0,
    "step": 55,
    "train_accuracy": 0.484375,
    "train_loss": 1.5061442852020264,
    "wall_clock_time_sec": 0.4481813907623291
  },
  {
    "ce_loss": 1.44033944606781,
    "learning_rate": 0.001,
    "pairwise_loss": 0.0,
    "resistance_supervision_loss": 0.0,
    "step": 56,
    "train_accuracy": 0.46875,
    "train_loss": 1.44033944606781,
    "wall_clock_time_sec": 0.4589269161224365
  },
  {
    "ce_loss": 1.362392783164978,
    "learning_rate": 0.001,
    "pairwise_loss": 0.0,
    "resistance_supervision_loss": 0.0,
    "step": 57,
    "train_accuracy": 0.46875,
    "train_loss": 1.362392783164978,
    "wall_clock_time_sec": 0.4677462577819824
  },
  {
    "ce_loss": 1.4040311574935913,
    "learning_rate": 0.001,
    "pairwise_loss": 0.0,
    "resistance_supervision_loss": 0.0,
    "step": 58,
    "train_accuracy": 0.5,
    "train_loss": 1.4040311574935913,
    "wall_clock_time_sec": 0.47365283966064453
  },
  {
    "ce_loss": 1.632406234741211,
    "learning_rate": 0.001,
    "pairwise_loss": 0.0,
    "resistance_supervision_loss": 0.0,
    "step": 59,
    "train_accuracy": 0.359375,
    "train_loss": 1.632406234741211,
    "wall_clock_time_sec": 0.4792349338531494
  },
  {
    "ce_loss": 1.530034065246582,
    "learning_rate": 0.001,
    "pairwise_loss": 0.0,
    "resistance_supervision_loss": 0.0,
    "step": 60,
    "train_accuracy": 0.40625,
    "train_loss": 1.530034065246582,
    "wall_clock_time_sec": 0.48357629776000977
  },
  {
    "ce_loss": 1.3929449319839478,
    "learning_rate": 0.001,
    "pairwise_loss": 0.0,
    "resistance_supervision_loss": 0.0,
    "step": 61,
    "train_accuracy": 0.53125,
    "train_loss": 1.3929449319839478,
    "wall_clock_time_sec": 0.48789358139038086
  },
  {
    "ce_loss": 1.267866849899292,
    "learning_rate": 0.001,
    "pairwise_loss": 0.0,
    "resistance_supervision_loss": 0.0,
    "step": 62,
    "train_accuracy": 0.453125,
    "train_loss": 1.267866849899292,
    "wall_clock_time_sec": 0.4915928840637207
  },
  {
    "ce_loss": 1.375851035118103,
    "learning_rate": 0.001,
    "pairwise_loss": 0.0,
    "resistance_supervision_loss": 0.0,
    "step": 63,
    "train_accuracy": 0.609375,
    "train_loss": 1.375851035118103,
    "wall_clock_time_sec": 0.4969947338104248
  },
  {
    "ce_loss": 1.4289969205856323,
    "learning_rate": 0.001,
    "pairwise_loss": 0.0,
    "resistance_supervision_loss": 0.0,
    "step": 64,
    "train_accuracy": 0.46875,
    "train_loss": 1.4289969205856323,
    "wall_clock_time_sec": 0.5009307861328125
  },
  {
    "ce_loss": 1.6069570779800415,
    "learning_rate": 0.001,
    "pairwise_loss": 0.0,
    "resistance_supervision_loss": 0.0,
    "step": 65,
    "train_accuracy": 0.484375,
    "train_loss": 1.6069570779800415,
    "wall_clock_time_sec": 0.5049569606781006
  },
  {
    "ce_loss": 1.3409963846206665,
    "learning_rate": 0.001,
    "pairwise_loss": 0.0,
    "resistance_supervision_loss": 0.0,
    "step": 66,
    "train_accuracy": 0.453125,
    "train_loss": 1.3409963846206665,
    "wall_clock_time_sec": 0.5135507583618164
  },
  {
    "ce_loss": 1.3815557956695557,
    "learning_rate": 0.001,
    "pairwise_loss": 0.0,
    "resistance_supervision_loss": 0.0,
    "step": 67,
    "train_accuracy": 0.5,
    "train_loss": 1.3815557956695557,
    "wall_clock_time_sec": 0.5176246166229248
  },
  {
    "ce_loss": 1.368170142173767,
    "learning_rate": 0.001,
    "pairwise_loss": 0.0,
    "resistance_supervision_loss": 0.0,
    "step": 68,
    "train_accuracy": 0.453125,
    "train_loss": 1.368170142173767,
    "wall_clock_time_sec": 0.5217187404632568
  },
  {
    "ce_loss": 1.5841403007507324,
    "learning_rate": 0.001,
    "pairwise_loss": 0.0,
    "resistance_supervision_loss": 0.0,
    "step": 69,
    "train_accuracy": 0.4375,
    "train_loss": 1.5841403007507324,
    "wall_clock_time_sec": 0.5261983871459961
  },
  {
    "ce_loss": 1.2086366415023804,
    "learning_rate": 0.001,
    "pairwise_loss": 0.0,
    "resistance_supervision_loss": 0.0,
    "step": 70,
    "train_accuracy": 0.609375,
    "train_loss": 1.2086366415023804,
    "wall_clock_time_sec": 0.53131103515625
  },
  {
    "ce_loss": 1.177746057510376,
    "learning_rate": 0.001,
    "pairwise_loss": 0.0,
    "resistance_supervision_loss": 0.0,
    "step": 71,
    "train_accuracy": 0.515625,
    "train_loss": 1.177746057510376,
    "wall_clock_time_sec": 0.5361654758453369
  },
  {
    "ce_loss": 1.2025935649871826,
    "learning_rate": 0.001,
    "pairwise_loss": 0.0,
    "resistance_supervision_loss": 0.0,
    "step": 72,
    "train_accuracy": 0.578125,
    "train_loss": 1.2025935649871826,
    "wall_clock_time_sec": 0.5405206680297852
  },
  {
    "ce_loss": 1.4225842952728271,
    "learning_rate": 0.001,
    "pairwise_loss": 0.0,
    "resistance_supervision_loss": 0.0,
    "step": 73,
    "train_accuracy": 0.46875,
    "train_loss": 1.4225842952728271,
    "wall_clock_time_sec": 0.5479388236999512
  },
  {
    "ce_loss": 1.3157870769500732,
    "learning_rate": 0.001,
    "pairwise_loss": 0.0,
    "resistance_supervision_loss": 0.0,
    "step": 74,
    "train_accuracy": 0.5625,
    "train_loss": 1.3157870769500732,
    "wall_clock_time_sec": 0.5527796745300293
  },
  {
    "ce_loss": 1.4644949436187744,
    "learning_rate": 0.001,
    "pairwise_loss": 0.0,
    "resistance_supervision_loss": 0.0,
    "step": 75,
    "train_accuracy": 0.46875,
    "train_loss": 1.4644949436187744,
    "val_accuracy": 0.4765625,
    "val_ece": 0.04943683743476868,
    "wall_clock_time_sec": 0.5580751895904541
  },
  {
    "ce_loss": 1.4114512205123901,
    "learning_rate": 0.001,
    "pairwise_loss": 0.0,
    "resistance_supervision_loss": 0.0,
    "step": 76,
    "train_accuracy": 0.515625,
    "train_loss": 1.4114512205123901,
    "wall_clock_time_sec": 0.6472558975219727
  },
  {
    "ce_loss": 1.4306081533432007,
    "learning_rate": 0.001,
    "pairwise_loss": 0.0,
    "resistance_supervision_loss": 0.0,
    "step": 77,
    "train_accuracy": 0.421875,
    "train_loss": 1.4306081533432007,
    "wall_clock_time_sec": 0.6520500183105469
  },
  {
    "ce_loss": 1.243796706199646,
    "learning_rate": 0.001,
    "pairwise_loss": 0.0,
    "resistance_supervision_loss": 0.0,
    "step": 78,
    "train_accuracy": 0.515625,
    "train_loss": 1.243796706199646,
    "wall_clock_time_sec": 0.6561779975891113
  },
  {
    "ce_loss": 1.366090178489685,
    "learning_rate": 0.001,
    "pairwise_loss": 0.0,
    "resistance_supervision_loss": 0.0,
    "step": 79,
    "train_accuracy": 0.46875,
    "train_loss": 1.366090178489685,
    "wall_clock_time_sec": 0.6610844135284424
  },
  {
    "ce_loss": 1.390960693359375,
    "learning_rate": 0.001,
    "pairwise_loss": 0.0,
    "resistance_supervision_loss": 0.0,
    "step": 80,
    "train_accuracy": 0.484375,
    "train_loss": 1.390960693359375,
    "wall_clock_time_sec": 0.6654725074768066
  },
  {
    "ce_loss": 1.3085328340530396,
    "learning_rate": 0.001,
    "pairwise_loss": 0.0,
    "resistance_supervision_loss": 0.0,
    "step": 81,
    "train_accuracy": 0.484375,
    "train_loss": 1.3085328340530396,
    "wall_clock_time_sec": 0.6703412532806396
  },
  {
    "ce_loss": 1.4804390668869019,
    "learning_rate": 0.001,
    "pairwise_loss": 0.0,
    "resistance_supervision_loss": 0.0,
    "step": 82,
    "train_accuracy": 0.40625,
    "train_loss": 1.4804390668869019,
    "wall_clock_time_sec": 0.6749594211578369
  },
  {
    "ce_loss": 1.4580814838409424,
    "learning_rate": 0.001,
    "pairwise_loss": 0.0,
    "resistance_supervision_loss": 0.0,
    "step": 83,
    "train_accuracy": 0.484375,
    "train_loss": 1.4580814838409424,
    "wall_clock_time_sec": 0.6797950267791748
  },
  {
    "ce_loss": 1.4141273498535156,
    "learning_rate": 0.001,
    "pairwise_loss": 0.0,
    "resistance_supervision_loss": 0.0,
    "step": 84,
    "train_accuracy": 0.421875,
    "train_loss": 1.4141273498535156,
    "wall_clock_time_sec": 0.6847412586212158
  },
  {
    "ce_loss": 1.3736821413040161,
    "learning_rate": 0.001,
    "pairwise_loss": 0.0,
    "resistance_supervision_loss": 0.0,
    "step": 85,
    "train_accuracy": 0.484375,
    "train_loss": 1.3736821413040161,
    "wall_clock_time_sec": 0.6950340270996094
  },
  {
    "ce_loss": 1.6033512353897095,
    "learning_rate": 0.001,
    "pairwise_loss": 0.0,
    "resistance_supervision_loss": 0.0,
    "step": 86,
    "train_accuracy": 0.390625,
    "train_loss": 1.6033512353897095,
    "wall_clock_time_sec": 0.7005012035369873
  },
  {
    "ce_loss": 1.1526671648025513,
    "learning_rate": 0.001,
    "pairwise_loss": 0.0,
    "resistance_supervision_loss": 0.0,
    "step": 87,
    "train_accuracy": 0.578125,
    "train_loss": 1.1526671648025513,
    "wall_clock_time_sec": 0.7055776119232178
  },
  {
    "ce_loss": 1.465830683708191,
    "learning_rate": 0.001,
    "pairwise_loss": 0.0,
    "resistance_supervision_loss": 0.0,
    "step": 88,
    "train_accuracy": 0.515625,
    "train_loss": 1.465830683708191,
    "wall_clock_time_sec": 0.710726261138916
  },
  {
    "ce_loss": 1.1810098886489868,
    "learning_rate": 0.001,
    "pairwise_loss": 0.0,
    "resistance_supervision_loss": 0.0,
    "step": 89,
    "train_accuracy": 0.625,
    "train_loss": 1.1810098886489868,
    "wall_clock_time_sec": 0.7162518501281738
  },
  {
    "ce_loss": 1.558350920677185,
    "learning_rate": 0.001,
    "pairwise_loss": 0.0,
    "resistance_supervision_loss": 0.0,
    "step": 90,
    "train_accuracy": 0.359375,
    "train_loss": 1.558350920677185,
    "wall_clock_time_sec": 0.72342848777771
  },
  {
    "ce_loss": 1.41399347782135,
    "learning_rate": 0.001,
    "pairwise_loss": 0.0,
    "resistance_supervision_loss": 0.0,
    "step": 91,
    "train_accuracy": 0.421875,
    "train_loss": 1.41399347782135,
    "wall_clock_time_sec": 0.7287266254425049
  },
  {
    "ce_loss": 1.4437141418457031,
    "learning_rate": 0.001,
    "pairwise_loss": 0.0,
    "resistance_supervision_loss": 0.0,
    "step": 92,
    "train_accuracy": 0.515625,
    "train_loss": 1.4437141418457031,
    "wall_clock_time_sec": 0.7339987754821777
  },
  {
    "ce_loss": 1.2321397066116333,
    "learning_rate": 0.001,
    "pairwise_loss": 0.0,
    "resistance_supervision_loss": 0.0,
    "step": 93,
    "train_accuracy": 0.53125,
    "train_loss": 1.2321397066116333,
    "wall_clock_time_sec": 0.7391574382781982
  },
  {
    "ce_loss": 1.3845603466033936,
    "learning_rate": 0.001,
    "pairwise_loss": 0.0,
    "resistance_supervision_loss": 0.0,
    "step": 94,
    "train_accuracy": 0.5,
    "train_loss": 1.3845603466033936,
    "wall_clock_time_sec": 0.7444350719451904
  },
  {
    "ce_loss": 1.3504420518875122,
    "learning_rate": 0.001,
    "pairwise_loss": 0.0,
    "resistance_supervision_loss": 0.0,
    "step": 95,
    "train_accuracy": 0.46875,
    "train_loss": 1.3504420518875122,
    "wall_clock_time_sec": 0.7496492862701416
  },
  {
    "ce_loss": 1.5964267253875732,
    "learning_rate": 0.001,
    "pairwise_loss": 0.0,
    "resistance_supervision_loss": 0.0,
    "step": 96,
    "train_accuracy": 0.46875,
    "train_loss": 1.5964267253875732,
    "wall_clock_time_sec": 0.7550625801086426
  },
  {
    "ce_loss": 1.2347264289855957,
    "learning_rate": 0.001,
    "pairwise_loss": 0.0,
    "resistance_supervision_loss": 0.0,
    "step": 97,
    "train_accuracy": 0.53125,
    "train_loss": 1.2347264289855957,
    "wall_clock_time_sec": 0.7598528861999512
  },
  {
    "ce_loss": 1.3345379829406738,
    "learning_rate": 0.001,
    "pairwise_loss": 0.0,
    "resistance_supervision_loss": 0.0,
    "step": 98,
    "train_accuracy": 0.46875,
    "train_loss": 1.3345379829406738,
    "wall_clock_time_sec": 0.7645907402038574
  },
  {
    "ce_loss": 1.305211067199707,
    "learning_rate": 0.001,
    "pairwise_loss": 0.0,
    "resistance_supervision_loss": 0.0,
    "step": 99,
    "train_accuracy": 0.53125,
    "train_loss": 1.305211067199707,
    "wall_clock_time_sec": 0.7695605754852295
  },
  {
    "ce_loss": 1.2436329126358032,
    "learning_rate": 0.001,
    "pairwise_loss": 0.0,
    "resistance_supervision_loss": 0.0,
    "step": 100,
    "train_accuracy": 0.578125,
    "train_loss": 1.2436329126358032,
    "val_accuracy": 0.45703125,
    "val_ece": 0.08003810793161392,
    "wall_clock_time_sec": 0.7748780250549316
  },
  {
    "ce_loss": 1.2623213529586792,
    "learning_rate": 0.001,
    "pairwise_loss": 0.0,
    "resistance_supervision_loss": 0.0,
    "step": 101,
    "train_accuracy": 0.5625,
    "train_loss": 1.2623213529586792,
    "wall_clock_time_sec": 0.8465752601623535
  },
  {
    "ce_loss": 1.3503504991531372,
    "learning_rate": 0.001,
    "pairwise_loss": 0.0,
    "resistance_supervision_loss": 0.0,
    "step": 102,
    "train_accuracy": 0.5,
    "train_loss": 1.3503504991531372,
    "wall_clock_time_sec": 0.8557114601135254
  },
  {
    "ce_loss": 1.283217430114746,
    "learning_rate": 0.001,
    "pairwise_loss": 0.0,
    "resistance_supervision_loss": 0.0,
    "step": 103,
    "train_accuracy": 0.546875,
    "train_loss": 1.283217430114746,
    "wall_clock_time_sec": 0.8607821464538574
  },
  {
    "ce_loss": 1.4020957946777344,
    "learning_rate": 0.001,
    "pairwise_loss": 0.0,
    "resistance_supervision_loss": 0.0,
    "step": 104,
    "train_accuracy": 0.5625,
    "train_loss": 1.4020957946777344,
    "wall_clock_time_sec": 0.8660104274749756
  },
  {
    "ce_loss": 1.2319968938827515,
    "learning_rate": 0.001,
    "pairwise_loss": 0.0,
    "resistance_supervision_loss": 0.0,
    "step": 105,
    "train_accuracy": 0.53125,
    "train_loss": 1.2319968938827515,
    "wall_clock_time_sec": 0.8711855411529541
  },
  {
    "ce_loss": 1.4626784324645996,
    "learning_rate": 0.001,
    "pairwise_loss": 0.0,
    "resistance_supervision_loss": 0.0,
    "step": 106,
    "train_accuracy": 0.484375,
    "train_loss": 1.4626784324645996,
    "wall_clock_time_sec": 0.876535177230835
  },
  {
    "ce_loss": 1.3455413579940796,
    "learning_rate": 0.001,
    "pairwise_loss": 0.0,
    "resistance_supervision_loss": 0.0,
    "step": 107,
    "train_accuracy": 0.546875,
    "train_loss": 1.3455413579940796,
    "wall_clock_time_sec": 0.8825054168701172
  },
  {
    "ce_loss": 1.2423814535140991,
    "learning_rate": 0.001,
    "pairwise_loss": 0.0,
    "resistance_supervision_loss": 0.0,
    "step": 108,
    "train_accuracy": 0.5,
    "train_loss": 1.2423814535140991,
    "wall_clock_time_sec": 0.8876760005950928
  },
  {
    "ce_loss": 1.0822104215621948,
    "learning_rate": 0.001,
    "pairwise_loss": 0.0,
    "resistance_supervision_loss": 0.0,
    "step": 109,
    "train_accuracy": 0.65625,
    "train_loss": 1.0822104215621948,
    "wall_clock_time_sec": 0.892709493637085
  },
  {
    "ce_loss": 1.2460901737213135,
    "learning_rate": 0.001,
    "pairwise_loss": 0.0,
    "resistance_supervision_loss": 0.0,
    "step": 110,
    "train_accuracy": 0.5,
    "train_loss": 1.2460901737213135,
    "wall_clock_time_sec": 0.8983476161956787
  },
  {
    "ce_loss": 1.2688791751861572,
    "learning_rate": 0.001,
    "pairwise_loss": 0.0,
    "resistance_supervision_loss": 0.0,
    "step": 111,
    "train_accuracy": 0.53125,
    "train_loss": 1.2688791751861572,
    "wall_clock_time_sec": 0.9040195941925049
  },
  {
    "ce_loss": 1.4156087636947632,
    "learning_rate": 0.001,
    "pairwise_loss": 0.0,
    "resistance_supervision_loss": 0.0,
    "step": 112,
    "train_accuracy": 0.5,
    "train_loss": 1.4156087636947632,
    "wall_clock_time_sec": 0.9097402095794678
  },
  {
    "ce_loss": 1.3145616054534912,
    "learning_rate": 0.001,
    "pairwise_loss": 0.0,
    "resistance_supervision_loss": 0.0,
    "step": 113,
    "train_accuracy": 0.515625,
    "train_loss": 1.3145616054534912,
    "wall_clock_time_sec": 0.915424108505249
  },
  {
    "ce_loss": 1.2038453817367554,
    "learning_rate": 0.001,
    "pairwise_loss": 0.0,
    "resistance_supervision_loss": 0.0,
    "step": 114,
    "train_accuracy": 0.5625,
    "train_loss": 1.2038453817367554,
    "wall_clock_time_sec": 0.9212191104888916
  },
  {
    "ce_loss": 1.4599436521530151,
    "learning_rate": 0.001,
    "pairwise_loss": 0.0,
    "resistance_supervision_loss": 0.0,
    "step": 115,
    "train_accuracy": 0.4375,
    "train_loss": 1.4599436521530151,
    "wall_clock_time_sec": 0.9274072647094727
  },
  {
    "ce_loss": 1.3722988367080688,
    "learning_rate": 0.001,
    "pairwise_loss": 0.0,
    "resistance_supervision_loss": 0.0,
    "step": 116,
    "train_accuracy": 0.515625,
    "train_loss": 1.3722988367080688,
    "wall_clock_time_sec": 0.9341604709625244
  },
  {
    "ce_loss": 1.2186739444732666,
    "learning_rate": 0.001,
    "pairwise_loss": 0.0,
    "resistance_supervision_loss": 0.0,
    "step": 117,
    "train_accuracy": 0.546875,
    "train_loss": 1.2186739444732666,
    "wall_clock_time_sec": 0.9424138069152832
  },
  {
    "ce_loss": 1.2092612981796265,
    "learning_rate": 0.001,
    "pairwise_loss": 0.0,
    "resistance_supervision_loss": 0.0,
    "step": 118,
    "train_accuracy": 0.609375,
    "train_loss": 1.2092612981796265,
    "wall_clock_time_sec": 0.9484784603118896
  },
  {
    "ce_loss": 1.2585586309432983,
    "learning_rate": 0.001,
    "pairwise_loss": 0.0,
    "resistance_supervision_loss": 0.0,
    "step": 119,
    "train_accuracy": 0.484375,
    "train_loss": 1.2585586309432983,
    "wall_clock_time_sec": 0.9538686275482178
  },
  {
    "ce_loss": 1.2291266918182373,
    "learning_rate": 0.001,
    "pairwise_loss": 0.0,
    "resistance_supervision_loss": 0.0,
    "step": 120,
    "train_accuracy": 0.546875,
    "train_loss": 1.2291266918182373,
    "wall_clock_time_sec": 0.9626309871673584
  },
  {
    "ce_loss": 1.13504159450531,
    "learning_rate": 0.001,
    "pairwise_loss": 0.0,
    "resistance_supervision_loss": 0.0,
    "step": 121,
    "train_accuracy": 0.515625,
    "train_loss": 1.13504159450531,
    "wall_clock_time_sec": 0.9685802459716797
  },
  {
    "ce_loss": 1.3761518001556396,
    "learning_rate": 0.001,
    "pairwise_loss": 0.0,
    "resistance_supervision_loss": 0.0,
    "step": 122,
    "train_accuracy": 0.46875,
    "train_loss": 1.3761518001556396,
    "wall_clock_time_sec": 0.9745883941650391
  },
  {
    "ce_loss": 1.357844591140747,
    "learning_rate": 0.001,
    "pairwise_loss": 0.0,
    "resistance_supervision_loss": 0.0,
    "step": 123,
    "train_accuracy": 0.546875,
    "train_loss": 1.357844591140747,
    "wall_clock_time_sec": 0.9807887077331543
  },
  {
    "ce_loss": 1.438262701034546,
    "learning_rate": 0.001,
    "pairwise_loss": 0.0,
    "resistance_supervision_loss": 0.0,
    "step": 124,
    "train_accuracy": 0.515625,
    "train_loss": 1.438262701034546,
    "wall_clock_time_sec": 0.98683762550354
  },
  {
    "ce_loss": 1.2217001914978027,
    "learning_rate": 0.001,
    "pairwise_loss": 0.0,
    "resistance_supervision_loss": 0.0,
    "step": 125,
    "train_accuracy": 0.53125,
    "train_loss": 1.2217001914978027,
    "val_accuracy": 0.49609375,
    "val_ece": 0.08993487805128098,
    "wall_clock_time_sec": 0.9932260513305664
  },
  {
    "ce_loss": 1.473422646522522,
    "learning_rate": 0.001,
    "pairwise_loss": 0.0,
    "resistance_supervision_loss": 0.0,
    "step": 126,
    "train_accuracy": 0.515625,
    "train_loss": 1.473422646522522,
    "wall_clock_time_sec": 1.0767230987548828
  },
  {
    "ce_loss": 1.4418679475784302,
    "learning_rate": 0.001,
    "pairwise_loss": 0.0,
    "resistance_supervision_loss": 0.0,
    "step": 127,
    "train_accuracy": 0.546875,
    "train_loss": 1.4418679475784302,
    "wall_clock_time_sec": 1.0863714218139648
  },
  {
    "ce_loss": 1.249777913093567,
    "learning_rate": 0.001,
    "pairwise_loss": 0.0,
    "resistance_supervision_loss": 0.0,
    "step": 128,
    "train_accuracy": 0.453125,
    "train_loss": 1.249777913093567,
    "wall_clock_time_sec": 1.0954415798187256
  },
  {
    "ce_loss": 1.2821948528289795,
    "learning_rate": 0.001,
    "pairwise_loss": 0.0,
    "resistance_supervision_loss": 0.0,
    "step": 129,
    "train_accuracy": 0.484375,
    "train_loss": 1.2821948528289795,
    "wall_clock_time_sec": 1.1014373302459717
  },
  {
    "ce_loss": 1.3279062509536743,
    "learning_rate": 0.001,
    "pairwise_loss": 0.0,
    "resistance_supervision_loss": 0.0,
    "step": 130,
    "train_accuracy": 0.5625,
    "train_loss": 1.3279062509536743,
    "wall_clock_time_sec": 1.1070022583007812
  },
  {
    "ce_loss": 1.2365459203720093,
    "learning_rate": 0.001,
    "pairwise_loss": 0.0,
    "resistance_supervision_loss": 0.0,
    "step": 131,
    "train_accuracy": 0.5,
    "train_loss": 1.2365459203720093,
    "wall_clock_time_sec": 1.1131186485290527
  },
  {
    "ce_loss": 1.3395503759384155,
    "learning_rate": 0.001,
    "pairwise_loss": 0.0,
    "resistance_supervision_loss": 0.0,
    "step": 132,
    "train_accuracy": 0.515625,
    "train_loss": 1.3395503759384155,
    "wall_clock_time_sec": 1.1198854446411133
  },
  {
    "ce_loss": 1.3718901872634888,
    "learning_rate": 0.001,
    "pairwise_loss": 0.0,
    "resistance_supervision_loss": 0.0,
    "step": 133,
    "train_accuracy": 0.46875,
    "train_loss": 1.3718901872634888,
    "wall_clock_time_sec": 1.126232624053955
  },
  {
    "ce_loss": 1.3261966705322266,
    "learning_rate": 0.001,
    "pairwise_loss": 0.0,
    "resistance_supervision_loss": 0.0,
    "step": 134,
    "train_accuracy": 0.5,
    "train_loss": 1.3261966705322266,
    "wall_clock_time_sec": 1.131934642791748
  },
  {
    "ce_loss": 1.3172801733016968,
    "learning_rate": 0.001,
    "pairwise_loss": 0.0,
    "resistance_supervision_loss": 0.0,
    "step": 135,
    "train_accuracy": 0.546875,
    "train_loss": 1.3172801733016968,
    "wall_clock_time_sec": 1.1385600566864014
  },
  {
    "ce_loss": 1.2872836589813232,
    "learning_rate": 0.001,
    "pairwise_loss": 0.0,
    "resistance_supervision_loss": 0.0,
    "step": 136,
    "train_accuracy": 0.515625,
    "train_loss": 1.2872836589813232,
    "wall_clock_time_sec": 1.1449851989746094
  },
  {
    "ce_loss": 1.2555687427520752,
    "learning_rate": 0.001,
    "pairwise_loss": 0.0,
    "resistance_supervision_loss": 0.0,
    "step": 137,
    "train_accuracy": 0.46875,
    "train_loss": 1.2555687427520752,
    "wall_clock_time_sec": 1.15460205078125
  },
  {
    "ce_loss": 1.257415533065796,
    "learning_rate": 0.001,
    "pairwise_loss": 0.0,
    "resistance_supervision_loss": 0.0,
    "step": 138,
    "train_accuracy": 0.5,
    "train_loss": 1.257415533065796,
    "wall_clock_time_sec": 1.1613783836364746
  },
  {
    "ce_loss": 1.3238162994384766,
    "learning_rate": 0.001,
    "pairwise_loss": 0.0,
    "resistance_supervision_loss": 0.0,
    "step": 139,
    "train_accuracy": 0.546875,
    "train_loss": 1.3238162994384766,
    "wall_clock_time_sec": 1.1679308414459229
  },
  {
    "ce_loss": 1.2489492893218994,
    "learning_rate": 0.001,
    "pairwise_loss": 0.0,
    "resistance_supervision_loss": 0.0,
    "step": 140,
    "train_accuracy": 0.5,
    "train_loss": 1.2489492893218994,
    "wall_clock_time_sec": 1.1744959354400635
  },
  {
    "ce_loss": 1.370909333229065,
    "learning_rate": 0.001,
    "pairwise_loss": 0.0,
    "resistance_supervision_loss": 0.0,
    "step": 141,
    "train_accuracy": 0.609375,
    "train_loss": 1.370909333229065,
    "wall_clock_time_sec": 1.181180715560913
  },
  {
    "ce_loss": 1.1493372917175293,
    "learning_rate": 0.001,
    "pairwise_loss": 0.0,
    "resistance_supervision_loss": 0.0,
    "step": 142,
    "train_accuracy": 0.59375,
    "train_loss": 1.1493372917175293,
    "wall_clock_time_sec": 1.1878106594085693
  },
  {
    "ce_loss": 1.2621785402297974,
    "learning_rate": 0.001,
    "pairwise_loss": 0.0,
    "resistance_supervision_loss": 0.0,
    "step": 143,
    "train_accuracy": 0.5625,
    "train_loss": 1.2621785402297974,
    "wall_clock_time_sec": 1.1939547061920166
  },
  {
    "ce_loss": 1.058156132698059,
    "learning_rate": 0.001,
    "pairwise_loss": 0.0,
    "resistance_supervision_loss": 0.0,
    "step": 144,
    "train_accuracy": 0.59375,
    "train_loss": 1.058156132698059,
    "wall_clock_time_sec": 1.2017974853515625
  },
  {
    "ce_loss": 1.3082878589630127,
    "learning_rate": 0.001,
    "pairwise_loss": 0.0,
    "resistance_supervision_loss": 0.0,
    "step": 145,
    "train_accuracy": 0.484375,
    "train_loss": 1.3082878589630127,
    "wall_clock_time_sec": 1.2092299461364746
  },
  {
    "ce_loss": 1.2490302324295044,
    "learning_rate": 0.001,
    "pairwise_loss": 0.0,
    "resistance_supervision_loss": 0.0,
    "step": 146,
    "train_accuracy": 0.546875,
    "train_loss": 1.2490302324295044,
    "wall_clock_time_sec": 1.2163736820220947
  },
  {
    "ce_loss": 1.2867085933685303,
    "learning_rate": 0.001,
    "pairwise_loss": 0.0,
    "resistance_supervision_loss": 0.0,
    "step": 147,
    "train_accuracy": 0.5625,
    "train_loss": 1.2867085933685303,
    "wall_clock_time_sec": 1.2635564804077148
  },
  {
    "ce_loss": 1.396239161491394,
    "learning_rate": 0.001,
    "pairwise_loss": 0.0,
    "resistance_supervision_loss": 0.0,
    "step": 148,
    "train_accuracy": 0.515625,
    "train_loss": 1.396239161491394,
    "wall_clock_time_sec": 1.2710590362548828
  },
  {
    "ce_loss": 1.3258429765701294,
    "learning_rate": 0.001,
    "pairwise_loss": 0.0,
    "resistance_supervision_loss": 0.0,
    "step": 149,
    "train_accuracy": 0.546875,
    "train_loss": 1.3258429765701294,
    "wall_clock_time_sec": 1.2777729034423828
  },
  {
    "ce_loss": 1.4730217456817627,
    "learning_rate": 0.001,
    "pairwise_loss": 0.0,
    "resistance_supervision_loss": 0.0,
    "step": 150,
    "train_accuracy": 0.46875,
    "train_loss": 1.4730217456817627,
    "val_accuracy": 0.49609375,
    "val_ece": 0.07418101280927658,
    "wall_clock_time_sec": 1.2845118045806885
  },
  {
    "ce_loss": 1.3644317388534546,
    "learning_rate": 0.001,
    "pairwise_loss": 0.0,
    "resistance_supervision_loss": 0.0,
    "step": 151,
    "train_accuracy": 0.484375,
    "train_loss": 1.3644317388534546,
    "wall_clock_time_sec": 1.3594400882720947
  },
  {
    "ce_loss": 1.1371822357177734,
    "learning_rate": 0.001,
    "pairwise_loss": 0.0,
    "resistance_supervision_loss": 0.0,
    "step": 152,
    "train_accuracy": 0.625,
    "train_loss": 1.1371822357177734,
    "wall_clock_time_sec": 1.3661460876464844
  },
  {
    "ce_loss": 1.530536413192749,
    "learning_rate": 0.001,
    "pairwise_loss": 0.0,
    "resistance_supervision_loss": 0.0,
    "step": 153,
    "train_accuracy": 0.5,
    "train_loss": 1.530536413192749,
    "wall_clock_time_sec": 1.3735291957855225
  },
  {
    "ce_loss": 1.3746167421340942,
    "learning_rate": 0.001,
    "pairwise_loss": 0.0,
    "resistance_supervision_loss": 0.0,
    "step": 154,
    "train_accuracy": 0.53125,
    "train_loss": 1.3746167421340942,
    "wall_clock_time_sec": 1.380277395248413
  },
  {
    "ce_loss": 1.2592397928237915,
    "learning_rate": 0.001,
    "pairwise_loss": 0.0,
    "resistance_supervision_loss": 0.0,
    "step": 155,
    "train_accuracy": 0.546875,
    "train_loss": 1.2592397928237915,
    "wall_clock_time_sec": 1.3881042003631592
  },
  {
    "ce_loss": 1.2598183155059814,
    "learning_rate": 0.001,
    "pairwise_loss": 0.0,
    "resistance_supervision_loss": 0.0,
    "step": 156,
    "train_accuracy": 0.5625,
    "train_loss": 1.2598183155059814,
    "wall_clock_time_sec": 1.3946099281311035
  },
  {
    "ce_loss": 1.402448058128357,
    "learning_rate": 0.001,
    "pairwise_loss": 0.0,
    "resistance_supervision_loss": 0.0,
    "step": 157,
    "train_accuracy": 0.515625,
    "train_loss": 1.402448058128357,
    "wall_clock_time_sec": 1.400770902633667
  },
  {
    "ce_loss": 1.0981484651565552,
    "learning_rate": 0.001,
    "pairwise_loss": 0.0,
    "resistance_supervision_loss": 0.0,
    "step": 158,
    "train_accuracy": 0.5625,
    "train_loss": 1.0981484651565552,
    "wall_clock_time_sec": 1.4072329998016357
  },
  {
    "ce_loss": 1.5624626874923706,
    "learning_rate": 0.001,
    "pairwise_loss": 0.0,
    "resistance_supervision_loss": 0.0,
    "step": 159,
    "train_accuracy": 0.53125,
    "train_loss": 1.5624626874923706,
    "wall_clock_time_sec": 1.4138102531433105
  },
  {
    "ce_loss": 1.3474702835083008,
    "learning_rate": 0.001,
    "pairwise_loss": 0.0,
    "resistance_supervision_loss": 0.0,
    "step": 160,
    "train_accuracy": 0.5,
    "train_loss": 1.3474702835083008,
    "wall_clock_time_sec": 1.4204413890838623
  },
  {
    "ce_loss": 1.22211492061615,
    "learning_rate": 0.001,
    "pairwise_loss": 0.0,
    "resistance_supervision_loss": 0.0,
    "step": 161,
    "train_accuracy": 0.546875,
    "train_loss": 1.22211492061615,
    "wall_clock_time_sec": 1.4277219772338867
  },
  {
    "ce_loss": 1.3190361261367798,
    "learning_rate": 0.001,
    "pairwise_loss": 0.0,
    "resistance_supervision_loss": 0.0,
    "step": 162,
    "train_accuracy": 0.484375,
    "train_loss": 1.3190361261367798,
    "wall_clock_time_sec": 1.4340388774871826
  },
  {
    "ce_loss": 1.4417980909347534,
    "learning_rate": 0.001,
    "pairwise_loss": 0.0,
    "resistance_supervision_loss": 0.0,
    "step": 163,
    "train_accuracy": 0.46875,
    "train_loss": 1.4417980909347534,
    "wall_clock_time_sec": 1.4403467178344727
  },
  {
    "ce_loss": 1.3452303409576416,
    "learning_rate": 0.001,
    "pairwise_loss": 0.0,
    "resistance_supervision_loss": 0.0,
    "step": 164,
    "train_accuracy": 0.515625,
    "train_loss": 1.3452303409576416,
    "wall_clock_time_sec": 1.4466571807861328
  },
  {
    "ce_loss": 1.2851558923721313,
    "learning_rate": 0.001,
    "pairwise_loss": 0.0,
    "resistance_supervision_loss": 0.0,
    "step": 165,
    "train_accuracy": 0.53125,
    "train_loss": 1.2851558923721313,
    "wall_clock_time_sec": 1.4529986381530762
  },
  {
    "ce_loss": 1.39193594455719,
    "learning_rate": 0.001,
    "pairwise_loss": 0.0,
    "resistance_supervision_loss": 0.0,
    "step": 166,
    "train_accuracy": 0.484375,
    "train_loss": 1.39193594455719,
    "wall_clock_time_sec": 1.4636831283569336
  },
  {
    "ce_loss": 1.3118582963943481,
    "learning_rate": 0.001,
    "pairwise_loss": 0.0,
    "resistance_supervision_loss": 0.0,
    "step": 167,
    "train_accuracy": 0.546875,
    "train_loss": 1.3118582963943481,
    "wall_clock_time_sec": 1.4730780124664307
  },
  {
    "ce_loss": 1.4363137483596802,
    "learning_rate": 0.001,
    "pairwise_loss": 0.0,
    "resistance_supervision_loss": 0.0,
    "step": 168,
    "train_accuracy": 0.453125,
    "train_loss": 1.4363137483596802,
    "wall_clock_time_sec": 1.480731725692749
  },
  {
    "ce_loss": 1.1722816228866577,
    "learning_rate": 0.001,
    "pairwise_loss": 0.0,
    "resistance_supervision_loss": 0.0,
    "step": 169,
    "train_accuracy": 0.5625,
    "train_loss": 1.1722816228866577,
    "wall_clock_time_sec": 1.4881353378295898
  },
  {
    "ce_loss": 1.3053172826766968,
    "learning_rate": 0.001,
    "pairwise_loss": 0.0,
    "resistance_supervision_loss": 0.0,
    "step": 170,
    "train_accuracy": 0.546875,
    "train_loss": 1.3053172826766968,
    "wall_clock_time_sec": 1.4959049224853516
  },
  {
    "ce_loss": 1.3980119228363037,
    "learning_rate": 0.001,
    "pairwise_loss": 0.0,
    "resistance_supervision_loss": 0.0,
    "step": 171,
    "train_accuracy": 0.515625,
    "train_loss": 1.3980119228363037,
    "wall_clock_time_sec": 1.5037219524383545
  },
  {
    "ce_loss": 1.3619892597198486,
    "learning_rate": 0.001,
    "pairwise_loss": 0.0,
    "resistance_supervision_loss": 0.0,
    "step": 172,
    "train_accuracy": 0.515625,
    "train_loss": 1.3619892597198486,
    "wall_clock_time_sec": 1.5115227699279785
  },
  {
    "ce_loss": 1.2034913301467896,
    "learning_rate": 0.001,
    "pairwise_loss": 0.0,
    "resistance_supervision_loss": 0.0,
    "step": 173,
    "train_accuracy": 0.515625,
    "train_loss": 1.2034913301467896,
    "wall_clock_time_sec": 1.5193984508514404
  },
  {
    "ce_loss": 1.299696445465088,
    "learning_rate": 0.001,
    "pairwise_loss": 0.0,
    "resistance_supervision_loss": 0.0,
    "step": 174,
    "train_accuracy": 0.5625,
    "train_loss": 1.299696445465088,
    "wall_clock_time_sec": 1.5270345211029053
  },
  {
    "ce_loss": 1.1684600114822388,
    "learning_rate": 0.001,
    "pairwise_loss": 0.0,
    "resistance_supervision_loss": 0.0,
    "step": 175,
    "train_accuracy": 0.5625,
    "train_loss": 1.1684600114822388,
    "val_accuracy": 0.46484375,
    "val_ece": 0.08319913595914841,
    "wall_clock_time_sec": 1.5347025394439697
  },
  {
    "ce_loss": 1.273206353187561,
    "learning_rate": 0.001,
    "pairwise_loss": 0.0,
    "resistance_supervision_loss": 0.0,
    "step": 176,
    "train_accuracy": 0.609375,
    "train_loss": 1.273206353187561,
    "wall_clock_time_sec": 1.6087751388549805
  },
  {
    "ce_loss": 1.5517361164093018,
    "learning_rate": 0.001,
    "pairwise_loss": 0.0,
    "resistance_supervision_loss": 0.0,
    "step": 177,
    "train_accuracy": 0.453125,
    "train_loss": 1.5517361164093018,
    "wall_clock_time_sec": 1.6162450313568115
  },
  {
    "ce_loss": 1.2444548606872559,
    "learning_rate": 0.001,
    "pairwise_loss": 0.0,
    "resistance_supervision_loss": 0.0,
    "step": 178,
    "train_accuracy": 0.546875,
    "train_loss": 1.2444548606872559,
    "wall_clock_time_sec": 1.6230056285858154
  },
  {
    "ce_loss": 1.1242605447769165,
    "learning_rate": 0.001,
    "pairwise_loss": 0.0,
    "resistance_supervision_loss": 0.0,
    "step": 179,
    "train_accuracy": 0.546875,
    "train_loss": 1.1242605447769165,
    "wall_clock_time_sec": 1.6301181316375732
  },
  {
    "ce_loss": 1.2849011421203613,
    "learning_rate": 0.001,
    "pairwise_loss": 0.0,
    "resistance_supervision_loss": 0.0,
    "step": 180,
    "train_accuracy": 0.546875,
    "train_loss": 1.2849011421203613,
    "wall_clock_time_sec": 1.6373131275177002
  },
  {
    "ce_loss": 1.2416026592254639,
    "learning_rate": 0.001,
    "pairwise_loss": 0.0,
    "resistance_supervision_loss": 0.0,
    "step": 181,
    "train_accuracy": 0.546875,
    "train_loss": 1.2416026592254639,
    "wall_clock_time_sec": 1.6446592807769775
  },
  {
    "ce_loss": 1.046614170074463,
    "learning_rate": 0.001,
    "pairwise_loss": 0.0,
    "resistance_supervision_loss": 0.0,
    "step": 182,
    "train_accuracy": 0.59375,
    "train_loss": 1.046614170074463,
    "wall_clock_time_sec": 1.6540465354919434
  },
  {
    "ce_loss": 1.2508046627044678,
    "learning_rate": 0.001,
    "pairwise_loss": 0.0,
    "resistance_supervision_loss": 0.0,
    "step": 183,
    "train_accuracy": 0.546875,
    "train_loss": 1.2508046627044678,
    "wall_clock_time_sec": 1.6617801189422607
  },
  {
    "ce_loss": 1.4464435577392578,
    "learning_rate": 0.001,
    "pairwise_loss": 0.0,
    "resistance_supervision_loss": 0.0,
    "step": 184,
    "train_accuracy": 0.484375,
    "train_loss": 1.4464435577392578,
    "wall_clock_time_sec": 1.6699163913726807
  },
  {
    "ce_loss": 1.2865386009216309,
    "learning_rate": 0.001,
    "pairwise_loss": 0.0,
    "resistance_supervision_loss": 0.0,
    "step": 185,
    "train_accuracy": 0.546875,
    "train_loss": 1.2865386009216309,
    "wall_clock_time_sec": 1.677711009979248
  },
  {
    "ce_loss": 1.0949854850769043,
    "learning_rate": 0.001,
    "pairwise_loss": 0.0,
    "resistance_supervision_loss": 0.0,
    "step": 186,
    "train_accuracy": 0.609375,
    "train_loss": 1.0949854850769043,
    "wall_clock_time_sec": 1.6852328777313232
  },
  {
    "ce_loss": 1.459367036819458,
    "learning_rate": 0.001,
    "pairwise_loss": 0.0,
    "resistance_supervision_loss": 0.0,
    "step": 187,
    "train_accuracy": 0.5,
    "train_loss": 1.459367036819458,
    "wall_clock_time_sec": 1.6927497386932373
  },
  {
    "ce_loss": 1.1958576440811157,
    "learning_rate": 0.001,
    "pairwise_loss": 0.0,
    "resistance_supervision_loss": 0.0,
    "step": 188,
    "train_accuracy": 0.625,
    "train_loss": 1.1958576440811157,
    "wall_clock_time_sec": 1.7003817558288574
  },
  {
    "ce_loss": 1.2302342653274536,
    "learning_rate": 0.001,
    "pairwise_loss": 0.0,
    "resistance_supervision_loss": 0.0,
    "step": 189,
    "train_accuracy": 0.578125,
    "train_loss": 1.2302342653274536,
    "wall_clock_time_sec": 1.708470106124878
  },
  {
    "ce_loss": 1.259425401687622,
    "learning_rate": 0.001,
    "pairwise_loss": 0.0,
    "resistance_supervision_loss": 0.0,
    "step": 190,
    "train_accuracy": 0.5625,
    "train_loss": 1.259425401687622,
    "wall_clock_time_sec": 1.7167346477508545
  },
  {
    "ce_loss": 1.1838972568511963,
    "learning_rate": 0.001,
    "pairwise_loss": 0.0,
    "resistance_supervision_loss": 0.0,
    "step": 191,
    "train_accuracy": 0.71875,
    "train_loss": 1.1838972568511963,
    "wall_clock_time_sec": 1.7263453006744385
  },
  {
    "ce_loss": 1.327011227607727,
    "learning_rate": 0.001,
    "pairwise_loss": 0.0,
    "resistance_supervision_loss": 0.0,
    "step": 192,
    "train_accuracy": 0.53125,
    "train_loss": 1.327011227607727,
    "wall_clock_time_sec": 1.7347495555877686
  },
  {
    "ce_loss": 1.150229811668396,
    "learning_rate": 0.001,
    "pairwise_loss": 0.0,
    "resistance_supervision_loss": 0.0,
    "step": 193,
    "train_accuracy": 0.625,
    "train_loss": 1.150229811668396,
    "wall_clock_time_sec": 1.743138313293457
  },
  {
    "ce_loss": 1.2335131168365479,
    "learning_rate": 0.001,
    "pairwise_loss": 0.0,
    "resistance_supervision_loss": 0.0,
    "step": 194,
    "train_accuracy": 0.578125,
    "train_loss": 1.2335131168365479,
    "wall_clock_time_sec": 1.7548139095306396
  },
  {
    "ce_loss": 1.38235342502594,
    "learning_rate": 0.001,
    "pairwise_loss": 0.0,
    "resistance_supervision_loss": 0.0,
    "step": 195,
    "train_accuracy": 0.5,
    "train_loss": 1.38235342502594,
    "wall_clock_time_sec": 1.770256757736206
  },
  {
    "ce_loss": 1.5613514184951782,
    "learning_rate": 0.001,
    "pairwise_loss": 0.0,
    "resistance_supervision_loss": 0.0,
    "step": 196,
    "train_accuracy": 0.4375,
    "train_loss": 1.5613514184951782,
    "wall_clock_time_sec": 1.778566598892212
  },
  {
    "ce_loss": 1.2271771430969238,
    "learning_rate": 0.001,
    "pairwise_loss": 0.0,
    "resistance_supervision_loss": 0.0,
    "step": 197,
    "train_accuracy": 0.640625,
    "train_loss": 1.2271771430969238,
    "wall_clock_time_sec": 1.7869956493377686
  },
  {
    "ce_loss": 1.3559740781784058,
    "learning_rate": 0.001,
    "pairwise_loss": 0.0,
    "resistance_supervision_loss": 0.0,
    "step": 198,
    "train_accuracy": 0.484375,
    "train_loss": 1.3559740781784058,
    "wall_clock_time_sec": 1.7950379848480225
  },
  {
    "ce_loss": 1.0556211471557617,
    "learning_rate": 0.001,
    "pairwise_loss": 0.0,
    "resistance_supervision_loss": 0.0,
    "step": 199,
    "train_accuracy": 0.640625,
    "train_loss": 1.0556211471557617,
    "wall_clock_time_sec": 1.803128719329834
  },
  {
    "ce_loss": 1.3424391746520996,
    "learning_rate": 0.001,
    "pairwise_loss": 0.0,
    "resistance_supervision_loss": 0.0,
    "step": 200,
    "train_accuracy": 0.515625,
    "train_loss": 1.3424391746520996,
    "val_accuracy": 0.5,
    "val_ece": 0.07607525587081909,
    "wall_clock_time_sec": 1.8115661144256592
  },
  {
    "ce_loss": 1.2417513132095337,
    "learning_rate": 0.001,
    "pairwise_loss": 0.0,
    "resistance_supervision_loss": 0.0,
    "step": 201,
    "train_accuracy": 0.515625,
    "train_loss": 1.2417513132095337,
    "wall_clock_time_sec": 1.8891949653625488
  },
  {
    "ce_loss": 1.4758538007736206,
    "learning_rate": 0.001,
    "pairwise_loss": 0.0,
    "resistance_supervision_loss": 0.0,
    "step": 202,
    "train_accuracy": 0.4375,
    "train_loss": 1.4758538007736206,
    "wall_clock_time_sec": 1.897773027420044
  },
  {
    "ce_loss": 1.2677991390228271,
    "learning_rate": 0.001,
    "pairwise_loss": 0.0,
    "resistance_supervision_loss": 0.0,
    "step": 203,
    "train_accuracy": 0.5625,
    "train_loss": 1.2677991390228271,
    "wall_clock_time_sec": 1.9064195156097412
  },
  {
    "ce_loss": 1.0887882709503174,
    "learning_rate": 0.001,
    "pairwise_loss": 0.0,
    "resistance_supervision_loss": 0.0,
    "step": 204,
    "train_accuracy": 0.640625,
    "train_loss": 1.0887882709503174,
    "wall_clock_time_sec": 1.914149284362793
  },
  {
    "ce_loss": 1.6390867233276367,
    "learning_rate": 0.001,
    "pairwise_loss": 0.0,
    "resistance_supervision_loss": 0.0,
    "step": 205,
    "train_accuracy": 0.4375,
    "train_loss": 1.6390867233276367,
    "wall_clock_time_sec": 1.9217486381530762
  },
  {
    "ce_loss": 1.3022401332855225,
    "learning_rate": 0.001,
    "pairwise_loss": 0.0,
    "resistance_supervision_loss": 0.0,
    "step": 206,
    "train_accuracy": 0.484375,
    "train_loss": 1.3022401332855225,
    "wall_clock_time_sec": 1.9293453693389893
  },
  {
    "ce_loss": 1.247904896736145,
    "learning_rate": 0.001,
    "pairwise_loss": 0.0,
    "resistance_supervision_loss": 0.0,
    "step": 207,
    "train_accuracy": 0.5625,
    "train_loss": 1.247904896736145,
    "wall_clock_time_sec": 1.9382784366607666
  },
  {
    "ce_loss": 1.2490793466567993,
    "learning_rate": 0.001,
    "pairwise_loss": 0.0,
    "resistance_supervision_loss": 0.0,
    "step": 208,
    "train_accuracy": 0.5625,
    "train_loss": 1.2490793466567993,
    "wall_clock_time_sec": 1.9471004009246826
  },
  {
    "ce_loss": 1.3179192543029785,
    "learning_rate": 0.001,
    "pairwise_loss": 0.0,
    "resistance_supervision_loss": 0.0,
    "step": 209,
    "train_accuracy": 0.5625,
    "train_loss": 1.3179192543029785,
    "wall_clock_time_sec": 1.955967664718628
  },
  {
    "ce_loss": 1.0366941690444946,
    "learning_rate": 0.001,
    "pairwise_loss": 0.0,
    "resistance_supervision_loss": 0.0,
    "step": 210,
    "train_accuracy": 0.65625,
    "train_loss": 1.0366941690444946,
    "wall_clock_time_sec": 1.9648663997650146
  },
  {
    "ce_loss": 1.1267584562301636,
    "learning_rate": 0.001,
    "pairwise_loss": 0.0,
    "resistance_supervision_loss": 0.0,
    "step": 211,
    "train_accuracy": 0.625,
    "train_loss": 1.1267584562301636,
    "wall_clock_time_sec": 1.9742629528045654
  },
  {
    "ce_loss": 1.403973937034607,
    "learning_rate": 0.001,
    "pairwise_loss": 0.0,
    "resistance_supervision_loss": 0.0,
    "step": 212,
    "train_accuracy": 0.515625,
    "train_loss": 1.403973937034607,
    "wall_clock_time_sec": 1.9831321239471436
  },
  {
    "ce_loss": 1.2824902534484863,
    "learning_rate": 0.001,
    "pairwise_loss": 0.0,
    "resistance_supervision_loss": 0.0,
    "step": 213,
    "train_accuracy": 0.515625,
    "train_loss": 1.2824902534484863,
    "wall_clock_time_sec": 1.9909942150115967
  },
  {
    "ce_loss": 1.3712345361709595,
    "learning_rate": 0.001,
    "pairwise_loss": 0.0,
    "resistance_supervision_loss": 0.0,
    "step": 214,
    "train_accuracy": 0.484375,
    "train_loss": 1.3712345361709595,
    "wall_clock_time_sec": 1.9994597434997559
  },
  {
    "ce_loss": 1.4066907167434692,
    "learning_rate": 0.001,
    "pairwise_loss": 0.0,
    "resistance_supervision_loss": 0.0,
    "step": 215,
    "train_accuracy": 0.453125,
    "train_loss": 1.4066907167434692,
    "wall_clock_time_sec": 2.00827956199646
  },
  {
    "ce_loss": 1.39945650100708,
    "learning_rate": 0.001,
    "pairwise_loss": 0.0,
    "resistance_supervision_loss": 0.0,
    "step": 216,
    "train_accuracy": 0.421875,
    "train_loss": 1.39945650100708,
    "wall_clock_time_sec": 2.0173728466033936
  },
  {
    "ce_loss": 0.9838840961456299,
    "learning_rate": 0.001,
    "pairwise_loss": 0.0,
    "resistance_supervision_loss": 0.0,
    "step": 217,
    "train_accuracy": 0.65625,
    "train_loss": 0.9838840961456299,
    "wall_clock_time_sec": 2.0259385108947754
  },
  {
    "ce_loss": 1.696318507194519,
    "learning_rate": 0.001,
    "pairwise_loss": 0.0,
    "resistance_supervision_loss": 0.0,
    "step": 218,
    "train_accuracy": 0.4375,
    "train_loss": 1.696318507194519,
    "wall_clock_time_sec": 2.034872531890869
  },
  {
    "ce_loss": 1.4361279010772705,
    "learning_rate": 0.001,
    "pairwise_loss": 0.0,
    "resistance_supervision_loss": 0.0,
    "step": 219,
    "train_accuracy": 0.421875,
    "train_loss": 1.4361279010772705,
    "wall_clock_time_sec": 2.0438053607940674
  },
  {
    "ce_loss": 1.3092188835144043,
    "learning_rate": 0.001,
    "pairwise_loss": 0.0,
    "resistance_supervision_loss": 0.0,
    "step": 220,
    "train_accuracy": 0.578125,
    "train_loss": 1.3092188835144043,
    "wall_clock_time_sec": 2.0527424812316895
  },
  {
    "ce_loss": 1.4499863386154175,
    "learning_rate": 0.001,
    "pairwise_loss": 0.0,
    "resistance_supervision_loss": 0.0,
    "step": 221,
    "train_accuracy": 0.46875,
    "train_loss": 1.4499863386154175,
    "wall_clock_time_sec": 2.061542510986328
  },
  {
    "ce_loss": 1.216861367225647,
    "learning_rate": 0.001,
    "pairwise_loss": 0.0,
    "resistance_supervision_loss": 0.0,
    "step": 222,
    "train_accuracy": 0.59375,
    "train_loss": 1.216861367225647,
    "wall_clock_time_sec": 2.0707244873046875
  },
  {
    "ce_loss": 1.0667670965194702,
    "learning_rate": 0.001,
    "pairwise_loss": 0.0,
    "resistance_supervision_loss": 0.0,
    "step": 223,
    "train_accuracy": 0.609375,
    "train_loss": 1.0667670965194702,
    "wall_clock_time_sec": 2.079986572265625
  },
  {
    "ce_loss": 1.365381121635437,
    "learning_rate": 0.001,
    "pairwise_loss": 0.0,
    "resistance_supervision_loss": 0.0,
    "step": 224,
    "train_accuracy": 0.515625,
    "train_loss": 1.365381121635437,
    "wall_clock_time_sec": 2.0934088230133057
  },
  {
    "ce_loss": 1.2170794010162354,
    "learning_rate": 0.001,
    "pairwise_loss": 0.0,
    "resistance_supervision_loss": 0.0,
    "step": 225,
    "train_accuracy": 0.625,
    "train_loss": 1.2170794010162354,
    "val_accuracy": 0.48828125,
    "val_ece": 0.0859537273645401,
    "wall_clock_time_sec": 2.1025023460388184
  },
  {
    "ce_loss": 1.4510482549667358,
    "learning_rate": 0.001,
    "pairwise_loss": 0.0,
    "resistance_supervision_loss": 0.0,
    "step": 226,
    "train_accuracy": 0.546875,
    "train_loss": 1.4510482549667358,
    "wall_clock_time_sec": 2.147425413131714
  },
  {
    "ce_loss": 1.3432360887527466,
    "learning_rate": 0.001,
    "pairwise_loss": 0.0,
    "resistance_supervision_loss": 0.0,
    "step": 227,
    "train_accuracy": 0.53125,
    "train_loss": 1.3432360887527466,
    "wall_clock_time_sec": 2.1563644409179688
  },
  {
    "ce_loss": 1.3718067407608032,
    "learning_rate": 0.001,
    "pairwise_loss": 0.0,
    "resistance_supervision_loss": 0.0,
    "step": 228,
    "train_accuracy": 0.484375,
    "train_loss": 1.3718067407608032,
    "wall_clock_time_sec": 2.165952682495117
  },
  {
    "ce_loss": 1.4165865182876587,
    "learning_rate": 0.001,
    "pairwise_loss": 0.0,
    "resistance_supervision_loss": 0.0,
    "step": 229,
    "train_accuracy": 0.53125,
    "train_loss": 1.4165865182876587,
    "wall_clock_time_sec": 2.175572156906128
  },
  {
    "ce_loss": 1.0367579460144043,
    "learning_rate": 0.001,
    "pairwise_loss": 0.0,
    "resistance_supervision_loss": 0.0,
    "step": 230,
    "train_accuracy": 0.625,
    "train_loss": 1.0367579460144043,
    "wall_clock_time_sec": 2.1862034797668457
  },
  {
    "ce_loss": 1.484197735786438,
    "learning_rate": 0.001,
    "pairwise_loss": 0.0,
    "resistance_supervision_loss": 0.0,
    "step": 231,
    "train_accuracy": 0.515625,
    "train_loss": 1.484197735786438,
    "wall_clock_time_sec": 2.196119785308838
  },
  {
    "ce_loss": 1.2670001983642578,
    "learning_rate": 0.001,
    "pairwise_loss": 0.0,
    "resistance_supervision_loss": 0.0,
    "step": 232,
    "train_accuracy": 0.578125,
    "train_loss": 1.2670001983642578,
    "wall_clock_time_sec": 2.205171823501587
  },
  {
    "ce_loss": 1.1267033815383911,
    "learning_rate": 0.001,
    "pairwise_loss": 0.0,
    "resistance_supervision_loss": 0.0,
    "step": 233,
    "train_accuracy": 0.59375,
    "train_loss": 1.1267033815383911,
    "wall_clock_time_sec": 2.213573694229126
  },
  {
    "ce_loss": 1.2040438652038574,
    "learning_rate": 0.001,
    "pairwise_loss": 0.0,
    "resistance_supervision_loss": 0.0,
    "step": 234,
    "train_accuracy": 0.578125,
    "train_loss": 1.2040438652038574,
    "wall_clock_time_sec": 2.222383499145508
  },
  {
    "ce_loss": 1.0691415071487427,
    "learning_rate": 0.001,
    "pairwise_loss": 0.0,
    "resistance_supervision_loss": 0.0,
    "step": 235,
    "train_accuracy": 0.640625,
    "train_loss": 1.0691415071487427,
    "wall_clock_time_sec": 2.231900453567505
  },
  {
    "ce_loss": 1.1394762992858887,
    "learning_rate": 0.001,
    "pairwise_loss": 0.0,
    "resistance_supervision_loss": 0.0,
    "step": 236,
    "train_accuracy": 0.5625,
    "train_loss": 1.1394762992858887,
    "wall_clock_time_sec": 2.2417101860046387
  },
  {
    "ce_loss": 1.2551252841949463,
    "learning_rate": 0.001,
    "pairwise_loss": 0.0,
    "resistance_supervision_loss": 0.0,
    "step": 237,
    "train_accuracy": 0.515625,
    "train_loss": 1.2551252841949463,
    "wall_clock_time_sec": 2.251563310623169
  },
  {
    "ce_loss": 1.3581435680389404,
    "learning_rate": 0.001,
    "pairwise_loss": 0.0,
    "resistance_supervision_loss": 0.0,
    "step": 238,
    "train_accuracy": 0.5,
    "train_loss": 1.3581435680389404,
    "wall_clock_time_sec": 2.261242151260376
  },
  {
    "ce_loss": 1.2950024604797363,
    "learning_rate": 0.001,
    "pairwise_loss": 0.0,
    "resistance_supervision_loss": 0.0,
    "step": 239,
    "train_accuracy": 0.53125,
    "train_loss": 1.2950024604797363,
    "wall_clock_time_sec": 2.273155689239502
  },
  {
    "ce_loss": 1.3253116607666016,
    "learning_rate": 0.001,
    "pairwise_loss": 0.0,
    "resistance_supervision_loss": 0.0,
    "step": 240,
    "train_accuracy": 0.484375,
    "train_loss": 1.3253116607666016,
    "wall_clock_time_sec": 2.2818729877471924
  },
  {
    "ce_loss": 1.2053126096725464,
    "learning_rate": 0.001,
    "pairwise_loss": 0.0,
    "resistance_supervision_loss": 0.0,
    "step": 241,
    "train_accuracy": 0.546875,
    "train_loss": 1.2053126096725464,
    "wall_clock_time_sec": 2.2906205654144287
  },
  {
    "ce_loss": 1.3864907026290894,
    "learning_rate": 0.001,
    "pairwise_loss": 0.0,
    "resistance_supervision_loss": 0.0,
    "step": 242,
    "train_accuracy": 0.5,
    "train_loss": 1.3864907026290894,
    "wall_clock_time_sec": 2.299630880355835
  },
  {
    "ce_loss": 1.6213239431381226,
    "learning_rate": 0.001,
    "pairwise_loss": 0.0,
    "resistance_supervision_loss": 0.0,
    "step": 243,
    "train_accuracy": 0.40625,
    "train_loss": 1.6213239431381226,
    "wall_clock_time_sec": 2.3096213340759277
  },
  {
    "ce_loss": 1.1638338565826416,
    "learning_rate": 0.001,
    "pairwise_loss": 0.0,
    "resistance_supervision_loss": 0.0,
    "step": 244,
    "train_accuracy": 0.640625,
    "train_loss": 1.1638338565826416,
    "wall_clock_time_sec": 2.319864511489868
  },
  {
    "ce_loss": 1.2437199354171753,
    "learning_rate": 0.001,
    "pairwise_loss": 0.0,
    "resistance_supervision_loss": 0.0,
    "step": 245,
    "train_accuracy": 0.578125,
    "train_loss": 1.2437199354171753,
    "wall_clock_time_sec": 2.3295674324035645
  },
  {
    "ce_loss": 1.3735039234161377,
    "learning_rate": 0.001,
    "pairwise_loss": 0.0,
    "resistance_supervision_loss": 0.0,
    "step": 246,
    "train_accuracy": 0.484375,
    "train_loss": 1.3735039234161377,
    "wall_clock_time_sec": 2.3422393798828125
  },
  {
    "ce_loss": 1.4892619848251343,
    "learning_rate": 0.001,
    "pairwise_loss": 0.0,
    "resistance_supervision_loss": 0.0,
    "step": 247,
    "train_accuracy": 0.5,
    "train_loss": 1.4892619848251343,
    "wall_clock_time_sec": 2.351808547973633
  },
  {
    "ce_loss": 1.4680583477020264,
    "learning_rate": 0.001,
    "pairwise_loss": 0.0,
    "resistance_supervision_loss": 0.0,
    "step": 248,
    "train_accuracy": 0.5,
    "train_loss": 1.4680583477020264,
    "wall_clock_time_sec": 2.361541986465454
  },
  {
    "ce_loss": 1.0841491222381592,
    "learning_rate": 0.001,
    "pairwise_loss": 0.0,
    "resistance_supervision_loss": 0.0,
    "step": 249,
    "train_accuracy": 0.5,
    "train_loss": 1.0841491222381592,
    "wall_clock_time_sec": 2.3716185092926025
  },
  {
    "ce_loss": 1.577049732208252,
    "learning_rate": 0.001,
    "pairwise_loss": 0.0,
    "resistance_supervision_loss": 0.0,
    "step": 250,
    "train_accuracy": 0.3125,
    "train_loss": 1.577049732208252,
    "val_accuracy": 0.48828125,
    "val_ece": 0.07051411271095276,
    "wall_clock_time_sec": 2.381366491317749
  },
  {
    "ce_loss": 1.3042409420013428,
    "learning_rate": 0.001,
    "pairwise_loss": 0.0,
    "resistance_supervision_loss": 0.0,
    "step": 251,
    "train_accuracy": 0.46875,
    "train_loss": 1.3042409420013428,
    "wall_clock_time_sec": 2.4385714530944824
  },
  {
    "ce_loss": 1.155089020729065,
    "learning_rate": 0.001,
    "pairwise_loss": 0.0,
    "resistance_supervision_loss": 0.0,
    "step": 252,
    "train_accuracy": 0.578125,
    "train_loss": 1.155089020729065,
    "wall_clock_time_sec": 2.4491324424743652
  },
  {
    "ce_loss": 1.2484625577926636,
    "learning_rate": 0.001,
    "pairwise_loss": 0.0,
    "resistance_supervision_loss": 0.0,
    "step": 253,
    "train_accuracy": 0.5625,
    "train_loss": 1.2484625577926636,
    "wall_clock_time_sec": 2.466174364089966
  },
  {
    "ce_loss": 1.3117026090621948,
    "learning_rate": 0.001,
    "pairwise_loss": 0.0,
    "resistance_supervision_loss": 0.0,
    "step": 254,
    "train_accuracy": 0.515625,
    "train_loss": 1.3117026090621948,
    "wall_clock_time_sec": 2.484879493713379
  },
  {
    "ce_loss": 1.1281036138534546,
    "learning_rate": 0.001,
    "pairwise_loss": 0.0,
    "resistance_supervision_loss": 0.0,
    "step": 255,
    "train_accuracy": 0.53125,
    "train_loss": 1.1281036138534546,
    "wall_clock_time_sec": 2.4968512058258057
  },
  {
    "ce_loss": 1.1400450468063354,
    "learning_rate": 0.001,
    "pairwise_loss": 0.0,
    "resistance_supervision_loss": 0.0,
    "step": 256,
    "train_accuracy": 0.59375,
    "train_loss": 1.1400450468063354,
    "wall_clock_time_sec": 2.506462335586548
  },
  {
    "ce_loss": 1.2941228151321411,
    "learning_rate": 0.001,
    "pairwise_loss": 0.0,
    "resistance_supervision_loss": 0.0,
    "step": 257,
    "train_accuracy": 0.546875,
    "train_loss": 1.2941228151321411,
    "wall_clock_time_sec": 2.5154483318328857
  },
  {
    "ce_loss": 1.1227480173110962,
    "learning_rate": 0.001,
    "pairwise_loss": 0.0,
    "resistance_supervision_loss": 0.0,
    "step": 258,
    "train_accuracy": 0.625,
    "train_loss": 1.1227480173110962,
    "wall_clock_time_sec": 2.5313005447387695
  },
  {
    "ce_loss": 1.3294605016708374,
    "learning_rate": 0.001,
    "pairwise_loss": 0.0,
    "resistance_supervision_loss": 0.0,
    "step": 259,
    "train_accuracy": 0.546875,
    "train_loss": 1.3294605016708374,
    "wall_clock_time_sec": 2.5495378971099854
  },
  {
    "ce_loss": 1.1325738430023193,
    "learning_rate": 0.001,
    "pairwise_loss": 0.0,
    "resistance_supervision_loss": 0.0,
    "step": 260,
    "train_accuracy": 0.578125,
    "train_loss": 1.1325738430023193,
    "wall_clock_time_sec": 2.5642614364624023
  },
  {
    "ce_loss": 1.1365805864334106,
    "learning_rate": 0.001,
    "pairwise_loss": 0.0,
    "resistance_supervision_loss": 0.0,
    "step": 261,
    "train_accuracy": 0.59375,
    "train_loss": 1.1365805864334106,
    "wall_clock_time_sec": 2.5744502544403076
  },
  {
    "ce_loss": 1.252659559249878,
    "learning_rate": 0.001,
    "pairwise_loss": 0.0,
    "resistance_supervision_loss": 0.0,
    "step": 262,
    "train_accuracy": 0.515625,
    "train_loss": 1.252659559249878,
    "wall_clock_time_sec": 2.5836293697357178
  },
  {
    "ce_loss": 1.1939953565597534,
    "learning_rate": 0.001,
    "pairwise_loss": 0.0,
    "resistance_supervision_loss": 0.0,
    "step": 263,
    "train_accuracy": 0.578125,
    "train_loss": 1.1939953565597534,
    "wall_clock_time_sec": 2.5992190837860107
  },
  {
    "ce_loss": 1.3761157989501953,
    "learning_rate": 0.001,
    "pairwise_loss": 0.0,
    "resistance_supervision_loss": 0.0,
    "step": 264,
    "train_accuracy": 0.53125,
    "train_loss": 1.3761157989501953,
    "wall_clock_time_sec": 2.613168716430664
  },
  {
    "ce_loss": 1.119111180305481,
    "learning_rate": 0.001,
    "pairwise_loss": 0.0,
    "resistance_supervision_loss": 0.0,
    "step": 265,
    "train_accuracy": 0.578125,
    "train_loss": 1.119111180305481,
    "wall_clock_time_sec": 2.6273014545440674
  },
  {
    "ce_loss": 1.3849380016326904,
    "learning_rate": 0.001,
    "pairwise_loss": 0.0,
    "resistance_supervision_loss": 0.0,
    "step": 266,
    "train_accuracy": 0.46875,
    "train_loss": 1.3849380016326904,
    "wall_clock_time_sec": 2.6433591842651367
  },
  {
    "ce_loss": 1.2510409355163574,
    "learning_rate": 0.001,
    "pairwise_loss": 0.0,
    "resistance_supervision_loss": 0.0,
    "step": 267,
    "train_accuracy": 0.5625,
    "train_loss": 1.2510409355163574,
    "wall_clock_time_sec": 2.661022186279297
  },
  {
    "ce_loss": 1.5095006227493286,
    "learning_rate": 0.001,
    "pairwise_loss": 0.0,
    "resistance_supervision_loss": 0.0,
    "step": 268,
    "train_accuracy": 0.359375,
    "train_loss": 1.5095006227493286,
    "wall_clock_time_sec": 2.6785335540771484
  },
  {
    "ce_loss": 1.3300079107284546,
    "learning_rate": 0.001,
    "pairwise_loss": 0.0,
    "resistance_supervision_loss": 0.0,
    "step": 269,
    "train_accuracy": 0.53125,
    "train_loss": 1.3300079107284546,
    "wall_clock_time_sec": 2.6958987712860107
  },
  {
    "ce_loss": 1.3737280368804932,
    "learning_rate": 0.001,
    "pairwise_loss": 0.0,
    "resistance_supervision_loss": 0.0,
    "step": 270,
    "train_accuracy": 0.515625,
    "train_loss": 1.3737280368804932,
    "wall_clock_time_sec": 2.7165188789367676
  },
  {
    "ce_loss": 1.1015777587890625,
    "learning_rate": 0.001,
    "pairwise_loss": 0.0,
    "resistance_supervision_loss": 0.0,
    "step": 271,
    "train_accuracy": 0.59375,
    "train_loss": 1.1015777587890625,
    "wall_clock_time_sec": 2.7283475399017334
  },
  {
    "ce_loss": 1.3273701667785645,
    "learning_rate": 0.001,
    "pairwise_loss": 0.0,
    "resistance_supervision_loss": 0.0,
    "step": 272,
    "train_accuracy": 0.546875,
    "train_loss": 1.3273701667785645,
    "wall_clock_time_sec": 2.7382402420043945
  },
  {
    "ce_loss": 1.2582390308380127,
    "learning_rate": 0.001,
    "pairwise_loss": 0.0,
    "resistance_supervision_loss": 0.0,
    "step": 273,
    "train_accuracy": 0.546875,
    "train_loss": 1.2582390308380127,
    "wall_clock_time_sec": 2.748753786087036
  },
  {
    "ce_loss": 1.161077857017517,
    "learning_rate": 0.001,
    "pairwise_loss": 0.0,
    "resistance_supervision_loss": 0.0,
    "step": 274,
    "train_accuracy": 0.59375,
    "train_loss": 1.161077857017517,
    "wall_clock_time_sec": 2.7592577934265137
  },
  {
    "ce_loss": 1.0752817392349243,
    "learning_rate": 0.001,
    "pairwise_loss": 0.0,
    "resistance_supervision_loss": 0.0,
    "step": 275,
    "train_accuracy": 0.609375,
    "train_loss": 1.0752817392349243,
    "val_accuracy": 0.47265625,
    "val_ece": 0.11145433783531189,
    "wall_clock_time_sec": 2.7699151039123535
  },
  {
    "ce_loss": 1.3313989639282227,
    "learning_rate": 0.001,
    "pairwise_loss": 0.0,
    "resistance_supervision_loss": 0.0,
    "step": 276,
    "train_accuracy": 0.46875,
    "train_loss": 1.3313989639282227,
    "wall_clock_time_sec": 2.805785655975342
  },
  {
    "ce_loss": 1.3931162357330322,
    "learning_rate": 0.001,
    "pairwise_loss": 0.0,
    "resistance_supervision_loss": 0.0,
    "step": 277,
    "train_accuracy": 0.5,
    "train_loss": 1.3931162357330322,
    "wall_clock_time_sec": 2.8155949115753174
  },
  {
    "ce_loss": 1.2316502332687378,
    "learning_rate": 0.001,
    "pairwise_loss": 0.0,
    "resistance_supervision_loss": 0.0,
    "step": 278,
    "train_accuracy": 0.578125,
    "train_loss": 1.2316502332687378,
    "wall_clock_time_sec": 2.8263330459594727
  },
  {
    "ce_loss": 1.1338791847229004,
    "learning_rate": 0.001,
    "pairwise_loss": 0.0,
    "resistance_supervision_loss": 0.0,
    "step": 279,
    "train_accuracy": 0.59375,
    "train_loss": 1.1338791847229004,
    "wall_clock_time_sec": 2.8369152545928955
  },
  {
    "ce_loss": 1.2165802717208862,
    "learning_rate": 0.001,
    "pairwise_loss": 0.0,
    "resistance_supervision_loss": 0.0,
    "step": 280,
    "train_accuracy": 0.609375,
    "train_loss": 1.2165802717208862,
    "wall_clock_time_sec": 2.847447156906128
  },
  {
    "ce_loss": 1.2976888418197632,
    "learning_rate": 0.001,
    "pairwise_loss": 0.0,
    "resistance_supervision_loss": 0.0,
    "step": 281,
    "train_accuracy": 0.5625,
    "train_loss": 1.2976888418197632,
    "wall_clock_time_sec": 2.858891248703003
  },
  {
    "ce_loss": 1.312589168548584,
    "learning_rate": 0.001,
    "pairwise_loss": 0.0,
    "resistance_supervision_loss": 0.0,
    "step": 282,
    "train_accuracy": 0.53125,
    "train_loss": 1.312589168548584,
    "wall_clock_time_sec": 2.8693954944610596
  },
  {
    "ce_loss": 1.3512763977050781,
    "learning_rate": 0.001,
    "pairwise_loss": 0.0,
    "resistance_supervision_loss": 0.0,
    "step": 283,
    "train_accuracy": 0.546875,
    "train_loss": 1.3512763977050781,
    "wall_clock_time_sec": 2.879520893096924
  },
  {
    "ce_loss": 1.3421962261199951,
    "learning_rate": 0.001,
    "pairwise_loss": 0.0,
    "resistance_supervision_loss": 0.0,
    "step": 284,
    "train_accuracy": 0.53125,
    "train_loss": 1.3421962261199951,
    "wall_clock_time_sec": 2.889819383621216
  },
  {
    "ce_loss": 1.1790416240692139,
    "learning_rate": 0.001,
    "pairwise_loss": 0.0,
    "resistance_supervision_loss": 0.0,
    "step": 285,
    "train_accuracy": 0.546875,
    "train_loss": 1.1790416240692139,
    "wall_clock_time_sec": 2.900961399078369
  },
  {
    "ce_loss": 1.1696075201034546,
    "learning_rate": 0.001,
    "pairwise_loss": 0.0,
    "resistance_supervision_loss": 0.0,
    "step": 286,
    "train_accuracy": 0.53125,
    "train_loss": 1.1696075201034546,
    "wall_clock_time_sec": 2.9118306636810303
  },
  {
    "ce_loss": 1.126847505569458,
    "learning_rate": 0.001,
    "pairwise_loss": 0.0,
    "resistance_supervision_loss": 0.0,
    "step": 287,
    "train_accuracy": 0.609375,
    "train_loss": 1.126847505569458,
    "wall_clock_time_sec": 2.9224908351898193
  },
  {
    "ce_loss": 1.1952006816864014,
    "learning_rate": 0.001,
    "pairwise_loss": 0.0,
    "resistance_supervision_loss": 0.0,
    "step": 288,
    "train_accuracy": 0.578125,
    "train_loss": 1.1952006816864014,
    "wall_clock_time_sec": 2.9333431720733643
  },
  {
    "ce_loss": 1.2068438529968262,
    "learning_rate": 0.001,
    "pairwise_loss": 0.0,
    "resistance_supervision_loss": 0.0,
    "step": 289,
    "train_accuracy": 0.515625,
    "train_loss": 1.2068438529968262,
    "wall_clock_time_sec": 2.9437553882598877
  },
  {
    "ce_loss": 1.4832209348678589,
    "learning_rate": 0.001,
    "pairwise_loss": 0.0,
    "resistance_supervision_loss": 0.0,
    "step": 290,
    "train_accuracy": 0.5,
    "train_loss": 1.4832209348678589,
    "wall_clock_time_sec": 2.95439076423645
  },
  {
    "ce_loss": 1.1651333570480347,
    "learning_rate": 0.001,
    "pairwise_loss": 0.0,
    "resistance_supervision_loss": 0.0,
    "step": 291,
    "train_accuracy": 0.515625,
    "train_loss": 1.1651333570480347,
    "wall_clock_time_sec": 2.9649975299835205
  },
  {
    "ce_loss": 1.1116960048675537,
    "learning_rate": 0.001,
    "pairwise_loss": 0.0,
    "resistance_supervision_loss": 0.0,
    "step": 292,
    "train_accuracy": 0.578125,
    "train_loss": 1.1116960048675537,
    "wall_clock_time_sec": 2.9760653972625732
  },
  {
    "ce_loss": 1.1718122959136963,
    "learning_rate": 0.001,
    "pairwise_loss": 0.0,
    "resistance_supervision_loss": 0.0,
    "step": 293,
    "train_accuracy": 0.609375,
    "train_loss": 1.1718122959136963,
    "wall_clock_time_sec": 2.987175941467285
  },
  {
    "ce_loss": 1.387856125831604,
    "learning_rate": 0.001,
    "pairwise_loss": 0.0,
    "resistance_supervision_loss": 0.0,
    "step": 294,
    "train_accuracy": 0.46875,
    "train_loss": 1.387856125831604,
    "wall_clock_time_sec": 2.998162031173706
  },
  {
    "ce_loss": 1.4269551038742065,
    "learning_rate": 0.001,
    "pairwise_loss": 0.0,
    "resistance_supervision_loss": 0.0,
    "step": 295,
    "train_accuracy": 0.4375,
    "train_loss": 1.4269551038742065,
    "wall_clock_time_sec": 3.0093579292297363
  },
  {
    "ce_loss": 1.1996747255325317,
    "learning_rate": 0.001,
    "pairwise_loss": 0.0,
    "resistance_supervision_loss": 0.0,
    "step": 296,
    "train_accuracy": 0.5,
    "train_loss": 1.1996747255325317,
    "wall_clock_time_sec": 3.020881414413452
  },
  {
    "ce_loss": 1.3186811208724976,
    "learning_rate": 0.001,
    "pairwise_loss": 0.0,
    "resistance_supervision_loss": 0.0,
    "step": 297,
    "train_accuracy": 0.53125,
    "train_loss": 1.3186811208724976,
    "wall_clock_time_sec": 3.031050443649292
  },
  {
    "ce_loss": 1.202117919921875,
    "learning_rate": 0.001,
    "pairwise_loss": 0.0,
    "resistance_supervision_loss": 0.0,
    "step": 298,
    "train_accuracy": 0.484375,
    "train_loss": 1.202117919921875,
    "wall_clock_time_sec": 3.041421413421631
  },
  {
    "ce_loss": 1.1173803806304932,
    "learning_rate": 0.001,
    "pairwise_loss": 0.0,
    "resistance_supervision_loss": 0.0,
    "step": 299,
    "train_accuracy": 0.546875,
    "train_loss": 1.1173803806304932,
    "wall_clock_time_sec": 3.0523288249969482
  },
  {
    "ce_loss": 1.2268880605697632,
    "learning_rate": 0.001,
    "pairwise_loss": 0.0,
    "resistance_supervision_loss": 0.0,
    "step": 300,
    "train_accuracy": 0.59375,
    "train_loss": 1.2268880605697632,
    "val_accuracy": 0.5,
    "val_ece": 0.07664182037115097,
    "wall_clock_time_sec": 3.0633699893951416
  }
]